pt_pump_up/PT_Pump_Up.py
pt_pump_up/__init__.py
pt_pump_up/benchmarks/__init__.py
pt_pump_up/orm/Architecture.py
pt_pump_up/orm/Author.py
pt_pump_up/orm/Conference.py
pt_pump_up/orm/Dataset.py
pt_pump_up/orm/Hrefs.py
pt_pump_up/orm/Language.py
pt_pump_up/orm/License.py
pt_pump_up/orm/Metric.py
pt_pump_up/orm/Model.py
pt_pump_up/orm/NLPTask.py
pt_pump_up/orm/Publication.py
pt_pump_up/orm/Status.py
pt_pump_up/orm/__init__.py
pt_pump_up/papers_with_code/PapersWithCode.py
pt_pump_up/papers_with_code/__init__.py
pt_pump_up/rating/Preservation_Rating.py
pt_pump_up/rating/__init__.py
pt_pump_up-2.2.4.dist-info/METADATA
pt_pump_up-2.2.4.dist-info/WHEEL
pt_pump_up-2.2.4.dist-info/top_level.txt
pt_pump_up-2.2.4.dist-info/RECORD
